yapee.py
yapee-1.0.1.dist-info/LICENSE
yapee-1.0.1.dist-info/METADATA
yapee-1.0.1.dist-info/WHEEL
yapee-1.0.1.dist-info/RECORD
