Metadata-Version: 2.3
Name: yapee
Version: 1.0.1
Summary: Yet Another Python Event Emitter
License: MIT
Keywords: asyncio,zero-dependency,event-emitter
Author: Dmytro Tkachenko
Author-email: itsme@somespecial.one
Requires-Python: >=3.10
Classifier: Framework :: AsyncIO
Classifier: Development Status :: 5 - Production/Stable
Classifier: Intended Audience :: Developers
Classifier: Intended Audience :: Information Technology
Classifier: Topic :: Software Development
Classifier: Topic :: Software Development :: Libraries
Classifier: Topic :: Software Development :: Libraries :: Python Modules
Classifier: Operating System :: OS Independent
Classifier: Programming Language :: Python
Classifier: Programming Language :: Python :: 3
Classifier: Programming Language :: Python :: 3 :: Only
Classifier: Programming Language :: Python :: 3.10
Classifier: Programming Language :: Python :: 3.11
Classifier: Programming Language :: Python :: 3.12
Classifier: Programming Language :: Python :: 3.13
Classifier: Typing :: Typed
Project-URL: Bug Tracker, https://github.com/somespecialone/yapee/issues
Project-URL: Homepage, https://github.com/somespecialone/yapee
Project-URL: Repository, https://github.com/somespecialone/yapee
